MachSysS/__init__.py
MachSysS/_modidx.py
MachSysS/convert_feems_result_to_proto.py
MachSysS/convert_gymir_result_to_proto.py
MachSysS/convert_proto_timeseries.py
MachSysS/convert_to_feems.py
MachSysS/convert_to_protobuf.py
MachSysS/feems_result_pb2.py
MachSysS/feems_result_pb2.pyi
MachSysS/gymir_result_pb2.py
MachSysS/gymir_result_pb2.pyi
MachSysS/py.typed
MachSysS/system_structure_pb2.py
MachSysS/system_structure_pb2.pyi
MachSysS/utility.py
machsyss-0.7.7.dist-info/licenses/LICENSE
proto/__init__.py
tests/__init__.py
tests/test.py
tests/utility.py
tests/utility_compare_proto.py
machsyss-0.7.7.dist-info/METADATA
machsyss-0.7.7.dist-info/WHEEL
machsyss-0.7.7.dist-info/top_level.txt
machsyss-0.7.7.dist-info/RECORD
